clld_document_plugin/__init__.py
clld_document_plugin/datatables.py
clld_document_plugin/interfaces.py
clld_document_plugin/models.py
clld_document_plugin/util.py
clld_document_plugin/static/clld-chapter.css
clld_document_plugin/static/clld-document.css
clld_document_plugin/static/clld-document.js
clld_document_plugin/static/clld-slides.css
clld_document_plugin/static/clld-slides.js
clld_document_plugin/templates/document/chapter.mako
clld_document_plugin/templates/document/detail_html.mako
clld_document_plugin/templates/document/index_html.mako
clld_document_plugin/templates/document/slides.mako
clld_document_plugin/templates/topic/detail_html.mako
clld_document_plugin/templates/topic/index_html.mako
clld_document_plugin-0.0.5.dist-info/LICENSE
clld_document_plugin-0.0.5.dist-info/METADATA
clld_document_plugin-0.0.5.dist-info/WHEEL
clld_document_plugin-0.0.5.dist-info/top_level.txt
clld_document_plugin-0.0.5.dist-info/RECORD
